npac_calibration-0.2.4.dist-info/METADATA
npac_calibration-0.2.4.dist-info/WHEEL
npac_calibration-0.2.4.dist-info/entry_points.txt
npac_calibration-0.2.4.dist-info/licenses/LICENSE
npac_calibration/__init__.py
npac_calibration/main/__init__.py
npac_calibration/main/detector_calibration.py
npac_calibration/main/functions.py
npac_calibration/main/gaussian_fit.py
npac_calibration/main/peaks.py
npac_calibration/main/utils.py
npac_calibration/plots/__init__.py
npac_calibration/plots/plot.py
npac_calibration/read_data/__init__.py
npac_calibration/read_data/read_files.py
npac_calibration/solutions/__init__.py
npac_calibration/solutions/exercise_1.py
npac_calibration/solutions/exercise_2.py
npac_calibration/solutions/exercise_3.py
npac_calibration/solutions/exercise_4.py
npac_calibration-0.2.4.dist-info/RECORD
