Metadata-Version: 2.1
Name: npac_calibration
Version: 0.2.4
Summary: Detector Calibration Package for NPAC
Author-Email: Binh Nguyen <thi-yen-binh.nguyen@universite-paris-saclay.fr>
License: MIT
Requires-Python: >=3.11
Requires-Dist: npac-validator>=1.0.0
Requires-Dist: pandas>=2.3.3
Requires-Dist: flake8>=7.3.0
Requires-Dist: black>=25.12.0
Requires-Dist: scipy>=1.16.3
Requires-Dist: matplotlib>=3.10.7
Requires-Dist: mypy>=1.19.0
